remove_labels.cpython-310-darwin.so
raise_utils-2.5.2.dist-info/RECORD
raise_utils-2.5.2.dist-info/LICENSE
raise_utils-2.5.2.dist-info/WHEEL
raise_utils-2.5.2.dist-info/top_level.txt
raise_utils-2.5.2.dist-info/METADATA
raise_utils/__init__.py
raise_utils/metrics/metrics.py
raise_utils/metrics/__init__.py
raise_utils/metrics/impl.py
raise_utils/metrics/dist.py
raise_utils/experiments/__init__.py
raise_utils/experiments/experiment.py
raise_utils/utils/__init__.py
raise_utils/utils/data_utils.py
raise_utils/utils/utils.py
raise_utils/learners/rf.py
raise_utils/learners/tree.py
raise_utils/learners/multiclassdl.py
raise_utils/learners/feedforward.py
raise_utils/learners/__init__.py
raise_utils/learners/autoencoder.py
raise_utils/learners/logreg.py
raise_utils/learners/nb.py
raise_utils/learners/svm.py
raise_utils/learners/learner.py
raise_utils/transforms/remove_labels.pyx
raise_utils/transforms/null.py
raise_utils/transforms/remove_labels.c
raise_utils/transforms/__init__.py
raise_utils/transforms/inliers.py
raise_utils/transforms/cfs.py
raise_utils/transforms/transform.py
raise_utils/transforms/wfo.py
raise_utils/transforms/text/lda.py
raise_utils/transforms/text/tf.py
raise_utils/transforms/text/__init__.py
raise_utils/transforms/text/transform.py
raise_utils/transforms/text/tfidf.py
raise_utils/transforms/text/hashing.py
raise_utils/hooks/hooks.py
raise_utils/hooks/__init__.py
raise_utils/interpret/interpret.py
raise_utils/interpret/kw.py
raise_utils/interpret/scottknott.py
raise_utils/interpret/__init__.py
raise_utils/interpret/sk.py
raise_utils/hyperparams/multi_ghost.py
raise_utils/hyperparams/__init__.py
raise_utils/hyperparams/dodge.py
raise_utils/hyperparams/ghost.py
raise_utils/hyperparams/hpo.py
raise_utils/hyperparams/smoothie.py
raise_utils/data/__init__.py
raise_utils/data/data.py
