Metadata-Version: 2.1
Name: raise-utils
Version: 2.5.2
Summary: RAISE lab package
Home-page: https://github.com/yrahul3910/raise
Author: RAISE, NC State University
Author-email: Rahul Yedida <rahul.yedida@pm.me>
Requires-Python: <3.13,>=3.9
License-File: LICENSE
Requires-Dist: setuptools==75.5.0
Requires-Dist: pytest~=7.3.2
Requires-Dist: pytest-cov~=4.1.0
Requires-Dist: cvxopt~=1.3.1
Requires-Dist: pandas~=2.2.2
Requires-Dist: numpy==1.26.4
Requires-Dist: colorama~=0.4.6
Requires-Dist: hyperopt~=0.2.7
Requires-Dist: coverage~=7.2.7
Requires-Dist: scikit-learn~=1.5.1
Requires-Dist: imblearn~=0.0
Requires-Dist: bohb-hpo~=0.5.2
Requires-Dist: Cython~=0.29.24
Requires-Dist: tabulate~=0.8.9
Requires-Dist: keras<4.0.0,>=3.0.0
Requires-Dist: statsmodels~=0.14.0
Requires-Dist: tensorflow>=2.16.2
